br_army_knife-0.0.7.dist-info/METADATA
br_army_knife-0.0.7.dist-info/WHEEL
br_army_knife-0.0.7.dist-info/licenses/LICENSE
br_army_knife/__init__.py
br_army_knife/code.py
br_army_knife/configs.py
br_army_knife/files.py
br_army_knife/lists.py
br_army_knife/logs.py
br_army_knife/parallel.py
br_army_knife-0.0.7.dist-info/RECORD
