Metadata-Version: 2.1
Name: br_army_knife
Version: 0.0.7
Summary: Under construction. Common utilities tools in python.
Author-Email: Lucas Quaresma <lucas.quaresma1@gmail.com>
Classifier: Programming Language :: Python :: 3
Classifier: License :: OSI Approved :: MIT License
Classifier: Operating System :: OS Independent
Project-URL: Homepage, https://github.com/luksquaresma/br_army_knife
Project-URL: Issues, https://github.com/luksquaresma/br_army_knife/issues
Requires-Python: >=3.10
